todds_typecasting/__init__.py
todds_typecasting/todds_typecasting.py
todds_typecasting-2025.9.16.dist-info/METADATA
todds_typecasting-2025.9.16.dist-info/WHEEL
todds_typecasting-2025.9.16.dist-info/licenses/LICENSE
todds_typecasting-2025.9.16.dist-info/RECORD
