Metadata-Version: 2.4
Name: todds_typecasting
Version: 2025.9.16
Summary: A custom typecasting utility for Python
Project-URL: Homepage, https://github.com/tch521/todds_typecasting
Project-URL: Bug Tracker, https://github.com/tch521/todds_typecasting/issues
Author-email: Todd <73101886+tch521@users.noreply.github.com>
License-File: LICENSE
Classifier: License :: OSI Approved :: Apache Software License
Classifier: Operating System :: OS Independent
Classifier: Programming Language :: Python :: 3
Requires-Python: >=3.11
